django_uidfield/__init__.py
django_uidfield/fields.py
django_uidfield/misc.py
django_uidfield/models.py
django_uidfield/tests.py
django_uidfield-0.3.5.dist-info/LICENSE
django_uidfield-0.3.5.dist-info/METADATA
django_uidfield-0.3.5.dist-info/WHEEL
django_uidfield-0.3.5.dist-info/top_level.txt
django_uidfield-0.3.5.dist-info/RECORD
