Metadata-Version: 2.1
Name: django-uidfield
Version: 0.3.5
Summary: django-uidfield is a library which includes class UIDField for models.
Home-page: https://github.com/ivelum/django-uidfield/
Author: ivelum
Author-email: info@ivelum.com
License: MIT
Keywords: django model field
Classifier: Development Status :: 4 - Beta
Classifier: Environment :: Plugins
Classifier: Framework :: Django
Classifier: Intended Audience :: Developers
Classifier: License :: OSI Approved :: MIT License
Classifier: Programming Language :: Python
Classifier: Topic :: Software Development :: Libraries :: Python Modules
License-File: LICENSE
Requires-Dist: django
